README.txt
setup.cfg
setup.py
palora/__init__.py
palora.egg-info/PKG-INFO
palora.egg-info/SOURCES.txt
palora.egg-info/dependency_links.txt
palora.egg-info/requires.txt
palora.egg-info/top_level.txt