Metadata-Version: 1.2
Name: palora
Version: 3.1
Summary: Wrapper Class around cx_Oracle for Oracle Autonomous Database
Home-page: https://github.com/ipal0/palora
Author: Pal
Author-email: ipal00@outlook.com
License: GPL
Platform: UNKNOWN
Requires-Python: >=3
